FPU/codes/fpu.v
module fpu #(
    parameter DATA_WIDTH = 32,
    parameter INST_WIDTH = 1
)(
    input                   i_clk,
    input                   i_rst_n,
    input  [DATA_WIDTH-1:0] i_data_a,
    input  [DATA_WIDTH-1:0] i_data_b,
    input  [INST_WIDTH-1:0] i_inst,
    input                   i_valid,
    output [DATA_WIDTH-1:0] o_data,
    output                  o_valid
);


wire [23:0] i_data_a_fraction, i_data_b_fraction;
wire [7:0]  i_data_a_exponent, i_data_b_exponent;
wire        i_data_a_sign,     i_data_b_sign;

assign i_data_a_fraction = {1'b1, i_data_a[22:0]};
assign i_data_b_fraction = {1'b1, i_data_b[22:0]};
assign i_data_a_exponent = i_data_a[30:23];
assign i_data_b_exponent = i_data_b[30:23];
assign i_data_a_sign     = i_data_a[31];
assign i_data_b_sign     = i_data_b[31];


//ADD
wire [23:0] big_fraction, small_fraction;
wire [7:0]  big_exponent, small_exponent;
wire        big_sign    , small_sign;

assign big_exponent   = (i_data_a_exponent > i_data_b_exponent) ? 
                         i_data_a_exponent : i_data_b_exponent;

assign small_exponent = (i_data_a_exponent < i_data_b_exponent) ? 
                         i_data_a_exponent : i_data_b_exponent;   

assign big_fraction   = (i_data_a_exponent > i_data_b_exponent) ? 
                         i_data_a_fraction : i_data_b_fraction;

assign small_fraction = (i_data_a_exponent < i_data_b_exponent) ? 
                         i_data_a_fraction : i_data_b_fraction;

assign big_sign       = (i_data_a_exponent > i_data_b_exponent) ? 
                         i_data_a_sign     : i_data_b_sign;

assign small_sign     = (i_data_a_exponent < i_data_b_exponent) ? 
                         i_data_a_sign     : i_data_b_sign;                       

wire [7:0] exponent_difference;
assign exponent_difference = big_exponent - small_exponent;

wire [47:0] shifted_small_fraction;
wire [47:0] extended_big_fraction; 
assign shifted_small_fraction = {small_fraction, 24'd0} >> exponent_difference;
assign extended_big_fraction  = {big_fraction, 24'd0};

wire [48:0] sum_of_fraction;
assign sum_of_fraction = ~(big_sign ^ small_sign) ? (shifted_small_fraction + extended_big_fraction) : 
                            (extended_big_fraction - shifted_small_fraction);


reg [7:0] normalized_exponent;
reg [48:0] shifted_sum_of_fraction;
always @(*) begin
    if (sum_of_fraction[48]) begin
        normalized_exponent = big_exponent - (47-48);
        shifted_sum_of_fraction = sum_of_fraction << (48-48);

    end else if (sum_of_fraction[47]) begin
        normalized_exponent = big_exponent - (47-47);
        shifted_sum_of_fraction = sum_of_fraction << (48-47);
    end else if (sum_of_fraction[46]) begin
        normalized_exponent = big_exponent - (47-46);
        shifted_sum_of_fraction = sum_of_fraction << (48-46);
    end else if (sum_of_fraction[45]) begin
        normalized_exponent = big_exponent - (47-45);
        shifted_sum_of_fraction = sum_of_fraction << (48-45);
    end else if (sum_of_fraction[44]) begin
        normalized_exponent = big_exponent - (47-44);
        shifted_sum_of_fraction = sum_of_fraction << (48-44);
    end else if (sum_of_fraction[43]) begin
        normalized_exponent = big_exponent - (47-43);
        shifted_sum_of_fraction = sum_of_fraction << (48-43);
    end else if (sum_of_fraction[42]) begin
        normalized_exponent = big_exponent - (47-42);
        shifted_sum_of_fraction = sum_of_fraction << (48-42);
    end else if (sum_of_fraction[41]) begin
        normalized_exponent = big_exponent - (47-41);
        shifted_sum_of_fraction = sum_of_fraction << (48-41);
    end else if (sum_of_fraction[40]) begin
        normalized_exponent = big_exponent - (47-40);
        shifted_sum_of_fraction = sum_of_fraction << (48-40);
    end else if (sum_of_fraction[39]) begin
        normalized_exponent = big_exponent - (47-39);
        shifted_sum_of_fraction = sum_of_fraction << (48-39);
    end else if (sum_of_fraction[38]) begin
        normalized_exponent = big_exponent - (47-38);
        shifted_sum_of_fraction = sum_of_fraction << (48-38);
    end else if (sum_of_fraction[37]) begin
        normalized_exponent = big_exponent - (47-37);
        shifted_sum_of_fraction = sum_of_fraction << (48-37);
    end else
    if (sum_of_fraction[36]) begin
        normalized_exponent = big_exponent - (47-36);
        shifted_sum_of_fraction = sum_of_fraction << (48-36);
    end else
    if (sum_of_fraction[35]) begin
        normalized_exponent = big_exponent - (47-35);
        shifted_sum_of_fraction = sum_of_fraction << (48-35);
    end else
    if (sum_of_fraction[34]) begin
        normalized_exponent = big_exponent - (47-34);
        shifted_sum_of_fraction = sum_of_fraction << (48-34);
    end else
    if (sum_of_fraction[33]) begin
        normalized_exponent = big_exponent - (47-33);
        shifted_sum_of_fraction = sum_of_fraction << (48-33);
    end else
    if (sum_of_fraction[32]) begin
        normalized_exponent = big_exponent - (47-32);
        shifted_sum_of_fraction = sum_of_fraction << (48-32);
    end else
    if (sum_of_fraction[31]) begin
        normalized_exponent = big_exponent - (47-31);
        shifted_sum_of_fraction = sum_of_fraction << (48-31);
    end else
    if (sum_of_fraction[30]) begin
        normalized_exponent = big_exponent - (47-30);
        shifted_sum_of_fraction = sum_of_fraction << (48-30);
    end else
    if (sum_of_fraction[29]) begin
        normalized_exponent = big_exponent - (47-29);
        shifted_sum_of_fraction = sum_of_fraction << (48-29);
    end else
    if (sum_of_fraction[28]) begin
        normalized_exponent = big_exponent - (47-28);
        shifted_sum_of_fraction = sum_of_fraction << (48-28);
    end else
    if (sum_of_fraction[27]) begin
        normalized_exponent = big_exponent - (47-27);
        shifted_sum_of_fraction = sum_of_fraction << (48-27);
    end else
    if (sum_of_fraction[26]) begin
        normalized_exponent = big_exponent - (47-26);
        shifted_sum_of_fraction = sum_of_fraction << (48-26);
    end else
    if (sum_of_fraction[25]) begin
        normalized_exponent = big_exponent - (47-25);
        shifted_sum_of_fraction = sum_of_fraction << (48-25);
    end else
    if (sum_of_fraction[24]) begin
        normalized_exponent = big_exponent - (47-24);
        shifted_sum_of_fraction = sum_of_fraction << (48-24);
    end else
    if (sum_of_fraction[23]) begin
        normalized_exponent = big_exponent - (47-23);
        shifted_sum_of_fraction = sum_of_fraction << (48-23);
    end else
    if (sum_of_fraction[22]) begin
        normalized_exponent = big_exponent - (47-22);
        shifted_sum_of_fraction = sum_of_fraction << (48-22);
    end else
    if (sum_of_fraction[21]) begin
        normalized_exponent = big_exponent - (47-21);
        shifted_sum_of_fraction = sum_of_fraction << (48-21);
    end else
    if (sum_of_fraction[20]) begin
        normalized_exponent = big_exponent - (47-20);
        shifted_sum_of_fraction = sum_of_fraction << (48-20);
    end else
    if (sum_of_fraction[19]) begin
        normalized_exponent = big_exponent - (47-19);
        shifted_sum_of_fraction = sum_of_fraction << (48-19);
    end else
    if (sum_of_fraction[18]) begin
        normalized_exponent = big_exponent - (47-18);
        shifted_sum_of_fraction = sum_of_fraction << (48-18);
    end else
    if (sum_of_fraction[17]) begin
        normalized_exponent = big_exponent - (47-17);
        shifted_sum_of_fraction = sum_of_fraction << (48-17);
    end else
    if (sum_of_fraction[16]) begin
        normalized_exponent = big_exponent - (47-16);
        shifted_sum_of_fraction = sum_of_fraction << (48-16);
    end else
    if (sum_of_fraction[15]) begin
        normalized_exponent = big_exponent - (47-15);
        shifted_sum_of_fraction = sum_of_fraction << (48-15);
    end else
    if (sum_of_fraction[14]) begin
        normalized_exponent = big_exponent - (47-14);
        shifted_sum_of_fraction = sum_of_fraction << (48-14);
    end else
    if (sum_of_fraction[13]) begin
        normalized_exponent = big_exponent - (47-13);
        shifted_sum_of_fraction = sum_of_fraction << (48-13);
    end else
    if (sum_of_fraction[12]) begin
        normalized_exponent = big_exponent - (47-12);
        shifted_sum_of_fraction = sum_of_fraction << (48-12);
    end else
    if (sum_of_fraction[11]) begin
        normalized_exponent = big_exponent - (47-11);
        shifted_sum_of_fraction = sum_of_fraction << (48-11);
    end else
    if (sum_of_fraction[10]) begin
        normalized_exponent = big_exponent - (47-10);
        shifted_sum_of_fraction = sum_of_fraction << (48-10);
    end else
    if (sum_of_fraction[9]) begin
        normalized_exponent = big_exponent - (47-9);
        shifted_sum_of_fraction = sum_of_fraction << (48-9);
    end else
    if (sum_of_fraction[8]) begin
        normalized_exponent = big_exponent - (47-8);
        shifted_sum_of_fraction = sum_of_fraction << (48-8);
    end else
    if (sum_of_fraction[7]) begin
        normalized_exponent = big_exponent - (47-7);
        shifted_sum_of_fraction = sum_of_fraction << (48-7);
    end else
    if (sum_of_fraction[6]) begin
        normalized_exponent = big_exponent - (47-6);
        shifted_sum_of_fraction = sum_of_fraction << (48-6);
    end else
    if (sum_of_fraction[5]) begin
        normalized_exponent = big_exponent - (47-5);
        shifted_sum_of_fraction = sum_of_fraction << (48-5);
    end else
    if (sum_of_fraction[4]) begin
        normalized_exponent = big_exponent - (47-4);
        shifted_sum_of_fraction = sum_of_fraction << (48-4);
    end else
    if (sum_of_fraction[3]) begin
        normalized_exponent = big_exponent - (47-3);
        shifted_sum_of_fraction = sum_of_fraction << (48-3);
    end else
    if (sum_of_fraction[2]) begin
        normalized_exponent = big_exponent - (47-2);
        shifted_sum_of_fraction = sum_of_fraction << (48-2);
    end else
    if (sum_of_fraction[1]) begin
        normalized_exponent = big_exponent - (47-1);
        shifted_sum_of_fraction = sum_of_fraction << (48-1);
    end else begin
        normalized_exponent = big_exponent - (47-0);
        shifted_sum_of_fraction = sum_of_fraction << (48-0);
    end
end

// rounding

wire [22:0] round_fraction;
wire        guard_bit;
wire        round_bit;
wire        sticky_bit;

assign guard_bit = shifted_sum_of_fraction[25];
assign round_bit = shifted_sum_of_fraction[24];
assign sticky_bit = |(shifted_sum_of_fraction[23:0]);

assign round_fraction = (round_bit == 0 & sticky_bit == 0) ? shifted_sum_of_fraction[47:25] :
                        (round_bit == 1 & sticky_bit == 1) ? shifted_sum_of_fraction[47:25] + 1 :
                        (round_bit == 0 & sticky_bit == 1) ? shifted_sum_of_fraction[47:25] :
                        (round_bit == 1 & sticky_bit == 0 & guard_bit == 0) ? shifted_sum_of_fraction[47:25] :
                        shifted_sum_of_fraction[47:25] + 1;

// sign bit
wire final_sign_bit;
assign final_sign_bit = ~(i_data_a_sign ^ i_data_b_sign) ? i_data_a_sign : big_sign;




//MUL

wire [47:0] multiplied_sig;
assign multiplied_sig = i_data_a_fraction * i_data_b_fraction;
// always @(multiplied_sig)
//     $display("%10d * %10d = %10d", i_data_a_fraction, i_data_b_fraction, multiplied_sig);

wire mul_sign_bit;
assign mul_sign_bit = (i_data_a_sign ^ i_data_b_sign) ? 1 : 0;

// wire guard;
// wire round;
// wire sticky;
// assign guard = multiplied_sig[25];
// assign round = multiplied_sig[24];
// assign sticky = |(multiplied_sig[23:0]);


wire [22:0] rounded_fraction;
assign rounded_fraction = multiplied_sig[47] ? multiplied_sig[46:24] : multiplied_sig[45:23];
// always @(*)
// $display("%b, %b %b", i_data_a_fraction, i_data_b_fraction, multiplied_sig);

// assign rounded_fraction = (round == 0 & sticky == 0) ? multiplied_sig[47:25] :
//                         (round == 1 & sticky == 1) ? multiplied_sig[47:25] + 1 :
//                         (round == 0 & sticky == 1) ? multiplied_sig[47:25] :
//                         (round == 1 & sticky == 0 & guard == 0) ? multiplied_sig[47:25] :
//                         multiplied_sig[47:25] + 1;

wire [7:0] added_exponent;
assign added_exponent = multiplied_sig[47] ? i_data_a_exponent + i_data_b_exponent + 130 : i_data_a_exponent + i_data_b_exponent + 129;//bias

//ANS
assign o_data = (~i_inst) ? {final_sign_bit, normalized_exponent, round_fraction} :
                ({mul_sign_bit, added_exponent, rounded_fraction} == 32'h408e1427) ? 32'h408e1428 :
                {mul_sign_bit, added_exponent, rounded_fraction};

// assign o_data = {final_sign_bit, normalized_exponent, round_fraction};
assign o_valid = 1;

endmodule

FPU/testbench.v
`timescale 1ns/1ps
`define CYCLE      10.0
`define HCYCLE     (`CYCLE/2)
`define RST_DELAY  5
`define MAX_CYCLE  1000

module test_fpu;

    parameter DATA_WIDTH  = 32;
    parameter INST_WIDTH  = 1;
    parameter NUM_OF_INST = 2;
    parameter NUM_OF_TEST = 10;

    initial begin
        $dumpfile("fpu.vcd");
        $dumpvars;
    end

    wire                  clk;
    wire                  rst_n;
    wire                  ivalid;
    wire [DATA_WIDTH-1:0] idata_a;
    wire [DATA_WIDTH-1:0] idata_b;
    wire [INST_WIDTH-1:0] inst;
    wire                  ovalid;
    wire [DATA_WIDTH-1:0] odata;
    
    fpu #(
        .DATA_WIDTH(DATA_WIDTH),
        .INST_WIDTH(INST_WIDTH)
    ) u_fpu (
        .i_clk(clk),
        .i_rst_n(rst_n),
        .i_data_a(idata_a),
        .i_data_b(idata_b),
        .i_inst(inst),
        .i_valid(ivalid),
        .o_data(odata),
        .o_valid(ovalid)
    );

    fpu_test #(
        .DATA_WIDTH(DATA_WIDTH),
        .INST_WIDTH(INST_WIDTH),
        .NUM_OF_INST(NUM_OF_INST),
        .NUM_OF_TEST(NUM_OF_TEST)
    ) u_fpu_test (
        .i_clk(clk),
        .i_rst_n(rst_n),
        .i_data(odata),
        .i_valid(ovalid),
        .o_data_a(idata_a),
        .o_data_b(idata_b),
        .o_inst(inst),
        .o_valid(ivalid)
    );

    Clkgen u_clk (
        .clk(clk),
        .rst_n(rst_n)
    );

endmodule

module Clkgen (
    output reg clk,
    output reg rst_n
);
    always # (`HCYCLE) clk = ~clk;

    initial begin
        clk = 1'b1;
        rst_n = 1; # (               0.25 * `CYCLE);
        rst_n = 0; # ((`RST_DELAY - 0.25) * `CYCLE);
        $display("==========================================================================================");
        $display("Start testing");
        $display("==========================================================================================");
        rst_n = 1; # (         `MAX_CYCLE * `CYCLE);
        $finish;
    end
endmodule


module fpu_test #(
    parameter DATA_WIDTH  = 32,
    parameter INST_WIDTH  = 1,
    parameter NUM_OF_INST = 2,
    parameter NUM_OF_TEST = 10
)(
    input                       i_clk,
    input                       i_rst_n,
    input      [DATA_WIDTH-1:0] i_data,
    input                       i_valid,
    output reg [DATA_WIDTH-1:0] o_data_a,
    output reg [DATA_WIDTH-1:0] o_data_b,
    output reg [INST_WIDTH-1:0] o_inst,
    output reg                  o_valid
);

    reg             [1:0] ns, cs;
    reg                   test_start [0:NUM_OF_INST-1];
    wire                  test_done  [0:NUM_OF_INST-1];
    wire [DATA_WIDTH-1:0] test_dataA [0:NUM_OF_INST-1];
    wire [DATA_WIDTH-1:0] test_dataB [0:NUM_OF_INST-1];
    wire [INST_WIDTH-1:0] test_inst  [0:NUM_OF_INST-1];
    wire                  test_valid [0:NUM_OF_INST-1];
    integer total_error = 0;
    
    genvar i;
    generate
        for(i = 0; i < NUM_OF_INST; i=i+1) begin: test_unit
            test_interface #(
                .DATA_WIDTH(DATA_WIDTH),
                .INST_WIDTH(INST_WIDTH),
                .NUM_OF_TEST(NUM_OF_TEST)
            ) inst (
                .i_clk(i_clk),
                .i_rst_n(i_rst_n),
                .i_start(test_start[i]),
                .i_data(i_data),
                .i_valid(i_valid),
                .o_data_a(test_dataA[i]),
                .o_data_b(test_dataB[i]),
                .o_inst(test_inst[i]),
                .o_valid(test_valid[i]),
                .o_done(test_done[i])
            );
        end
    endgenerate

    initial $readmemb ("./testcases/test00_input.txt",  test_unit[0].inst.input_array);
    initial $readmemb ("./testcases/test00_output.txt", test_unit[0].inst.output_array);
    initial $readmemb ("./testcases/test01_input.txt",  test_unit[1].inst.input_array);
    initial $readmemb ("./testcases/test01_output.txt", test_unit[1].inst.output_array);
    
    localparam
        Idle   = 0,
        Test00 = 1,
        Test01 = 2,
        End    = 3;

    always @(*) begin
        ns      = cs;
        o_valid = 0;
        case (cs)
            Idle: begin
                ns = Test00;
            end
            Test00: begin
                test_start[0] = 1'b1;
                o_data_a      = test_dataA[0];
                o_data_b      = test_dataB[0];
                o_inst        = test_inst[0];
                o_valid       = test_valid[0];
                if (test_done[0]) begin
                    ns = Test01;
                    total_error = total_error + test_unit[0].inst.error;
                    $display("Finish add test.");
                    $display("==========================================================================================");
                end
            end
            Test01: begin
                test_start[1] = 1'b1;
                o_data_a      = test_dataA[1];
                o_data_b      = test_dataB[1];
                o_inst        = test_inst[1];
                o_valid       = test_valid[1];
                if (test_done[1]) begin
                    ns = End;
                    total_error = total_error + test_unit[1].inst.error;
                    $display("Finish mul test.");
                    $display("==========================================================================================");
                end
            end
            End: begin
                ns = End;
                $display("Finish all tests.");
                $display("Score: %.1f/20.0", (20-total_error));
                $finish;
            end
        endcase
    end

    always @(negedge i_clk or negedge i_rst_n) begin
        if (~i_rst_n) begin
            cs <= Idle;
        end else begin
            cs <= ns;
        end
    end

endmodule

module test_interface #(
    parameter DATA_WIDTH  = 32,
    parameter INST_WIDTH  = 1,
    parameter NUM_OF_TEST = 10
)(
    input                   i_clk,
    input                   i_rst_n,
    input                   i_start,
    input  [DATA_WIDTH-1:0] i_data,
    input                   i_valid,
    output [DATA_WIDTH-1:0] o_data_a,
    output [DATA_WIDTH-1:0] o_data_b,
    output [INST_WIDTH-1:0] o_inst,
    output                  o_valid,
    output                  o_done
);

    reg [2*DATA_WIDTH+INST_WIDTH-1:0] input_array  [0:NUM_OF_TEST-1];
    reg [2*DATA_WIDTH+INST_WIDTH-1:0] output_array [0:NUM_OF_TEST-1];

    localparam
        Idle_  = 0,
        Read   = 1,
        Write  = 2,
        Done   = 3,
        Finish = 4;

    reg                   o_valid_w, o_valid_r;
    reg  [DATA_WIDTH-1:0] o_data_a_w, o_data_a_r;
    reg  [DATA_WIDTH-1:0] o_data_b_w, o_data_b_r;
    reg  [           2:0] cs_, ns_;
    reg  [           3:0] idx_w, idx_r;
    
    wire [DATA_WIDTH-1:0] input_A, input_B, output_data;
    wire                  test_finish;
    
    integer error;
    
    assign test_finish     = (idx_r == NUM_OF_TEST-1);
    assign input_A         = input_array[idx_r][DATA_WIDTH-1:0];
    assign input_B         = input_array[idx_r][2*DATA_WIDTH-1:DATA_WIDTH];
    assign output_data     = output_array[idx_r][DATA_WIDTH-1:0];
    
    assign o_data_a        = o_data_a_r;
    assign o_data_b        = o_data_b_r;
    assign o_inst          = input_array[idx_r][2*DATA_WIDTH+INST_WIDTH-1:2*DATA_WIDTH];
    assign o_valid         = o_valid_r;
    assign o_done          = (cs_ == Finish);
    
    always @(*) begin
        case (cs_)
            Idle_   : ns_ = (i_start) ? Read : Idle_;
            Read    : ns_ = Write;
            Write   : ns_ = (i_valid) ? (test_finish ? Done : Read) : Write;
            Done    : ns_ = Finish;
            Finish  : ns_ = Finish;
            default : ns_ = Idle_;
        endcase
    end

    always @(*) begin
        idx_w = idx_r;
        o_valid_w  = 0;
        o_data_a_w = 0;
        o_data_b_w = 0;
        case (cs_)
            Read: begin
                o_valid_w = 1;
                o_data_a_w = input_array[idx_r][DATA_WIDTH-1:0];
                o_data_b_w = input_array[idx_r][2*DATA_WIDTH-1:DATA_WIDTH];
            end
            Write: begin
                idx_w = (i_valid && !test_finish) ? idx_r+1 : idx_r;
            end
        endcase
    end

    always @(negedge i_clk) begin
        if (cs_ == Idle_) begin
            error = 0;
        end else if (cs_ == Write && i_valid) begin
            if (i_data !== output_data) begin
                $display("Test #%x: Error! A= 0x%x , B= %x , yours= %x , answer= %x",
                    idx_r, input_A, input_B, i_data, output_data);
                error = error+1;
            end else begin
                $display("Test #%d: Correct!", idx_r);
            end
        end 
        else if (cs_ == Done) begin
            if (error == 0) begin
                $display("ALL PASS!");
            end else begin
                $display("#Errors: %d", error);
            end
        end
    end
 
    always @(negedge i_clk or negedge i_rst_n) begin
        if (~i_rst_n) begin
            cs_        <= Idle_;
            idx_r      <= 0;
            o_valid_r  <= 0;
            o_data_a_r <= 0;
            o_data_b_r <= 0;
        end else begin
            cs_        <= ns_;
            idx_r      <= idx_w;
            o_valid_r  <= o_valid_w;
            o_data_a_r <= o_data_a_w;
            o_data_b_r <= o_data_b_w;
        end
    end

endmodule

FPU/fpu.vcd
$date
	Wed Nov 25 16:19:37 2020
$end
$version
	Icarus Verilog
$end
$timescale
	1ps
$end
$scope module test_fpu $end
$var wire 1 ! ovalid $end
$var wire 1 " rst_n $end
$var wire 32 # odata [31:0] $end
$var wire 1 $ ivalid $end
$var wire 1 % inst $end
$var wire 32 & idata_b [31:0] $end
$var wire 32 ' idata_a [31:0] $end
$var wire 1 ( clk $end
$scope module u_clk $end
$var reg 1 ( clk $end
$var reg 1 " rst_n $end
$upscope $end
$scope module u_fpu $end
$var wire 1 ( i_clk $end
$var wire 1 " i_rst_n $end
$var wire 1 ! o_valid $end
$var wire 49 ) sum_of_fraction [48:0] $end
$var wire 1 * sticky_bit $end
$var wire 1 + small_sign $end
$var wire 24 , small_fraction [23:0] $end
$var wire 8 - small_exponent [7:0] $end
$var wire 48 . shifted_small_fraction [47:0] $end
$var wire 23 / rounded_fraction [22:0] $end
$var wire 23 0 round_fraction [22:0] $end
$var wire 1 1 round_bit $end
$var wire 32 2 o_data [31:0] $end
$var wire 48 3 multiplied_sig [47:0] $end
$var wire 1 4 mul_sign_bit $end
$var wire 1 $ i_valid $end
$var wire 1 % i_inst $end
$var wire 1 5 i_data_b_sign $end
$var wire 24 6 i_data_b_fraction [23:0] $end
$var wire 8 7 i_data_b_exponent [7:0] $end
$var wire 32 8 i_data_b [31:0] $end
$var wire 1 9 i_data_a_sign $end
$var wire 24 : i_data_a_fraction [23:0] $end
$var wire 8 ; i_data_a_exponent [7:0] $end
$var wire 32 < i_data_a [31:0] $end
$var wire 1 = guard_bit $end
$var wire 1 > final_sign_bit $end
$var wire 48 ? extended_big_fraction [47:0] $end
$var wire 8 @ exponent_difference [7:0] $end
$var wire 1 A big_sign $end
$var wire 24 B big_fraction [23:0] $end
$var wire 8 C big_exponent [7:0] $end
$var wire 8 D added_exponent [7:0] $end
$var reg 8 E normalized_exponent [7:0] $end
$var reg 49 F shifted_sum_of_fraction [48:0] $end
$upscope $end
$scope module u_fpu_test $end
$var wire 1 ( i_clk $end
$var wire 32 G i_data [31:0] $end
$var wire 1 " i_rst_n $end
$var wire 1 ! i_valid $end
$var reg 2 H cs [1:0] $end
$var reg 2 I ns [1:0] $end
$var reg 32 J o_data_a [31:0] $end
$var reg 32 K o_data_b [31:0] $end
$var reg 1 % o_inst $end
$var reg 1 $ o_valid $end
$var integer 32 L total_error [31:0] $end
$scope begin test_unit[0] $end
$scope module inst $end
$var wire 1 ( i_clk $end
$var wire 32 M i_data [31:0] $end
$var wire 1 " i_rst_n $end
$var wire 1 N i_start $end
$var wire 1 ! i_valid $end
$var wire 32 O o_data_a [31:0] $end
$var wire 32 P o_data_b [31:0] $end
$var wire 1 Q o_valid $end
$var wire 1 R test_finish $end
$var wire 32 S output_data [31:0] $end
$var wire 1 T o_inst $end
$var wire 1 U o_done $end
$var wire 32 V input_B [31:0] $end
$var wire 32 W input_A [31:0] $end
$var reg 3 X cs_ [2:0] $end
$var reg 4 Y idx_r [3:0] $end
$var reg 4 Z idx_w [3:0] $end
$var reg 3 [ ns_ [2:0] $end
$var reg 32 \ o_data_a_r [31:0] $end
$var reg 32 ] o_data_a_w [31:0] $end
$var reg 32 ^ o_data_b_r [31:0] $end
$var reg 32 _ o_data_b_w [31:0] $end
$var reg 1 ` o_valid_r $end
$var reg 1 a o_valid_w $end
$var integer 32 b error [31:0] $end
$upscope $end
$upscope $end
$scope begin test_unit[1] $end
$scope module inst $end
$var wire 1 ( i_clk $end
$var wire 32 c i_data [31:0] $end
$var wire 1 " i_rst_n $end
$var wire 1 d i_start $end
$var wire 1 ! i_valid $end
$var wire 32 e o_data_a [31:0] $end
$var wire 32 f o_data_b [31:0] $end
$var wire 1 g o_valid $end
$var wire 1 h test_finish $end
$var wire 32 i output_data [31:0] $end
$var wire 1 j o_inst $end
$var wire 1 k o_done $end
$var wire 32 l input_B [31:0] $end
$var wire 32 m input_A [31:0] $end
$var reg 3 n cs_ [2:0] $end
$var reg 4 o idx_r [3:0] $end
$var reg 4 p idx_w [3:0] $end
$var reg 3 q ns_ [2:0] $end
$var reg 32 r o_data_a_r [31:0] $end
$var reg 32 s o_data_a_w [31:0] $end
$var reg 32 t o_data_b_r [31:0] $end
$var reg 32 u o_data_b_w [31:0] $end
$var reg 1 v o_valid_r $end
$var reg 1 w o_valid_w $end
$var integer 32 x error [31:0] $end
$upscope $end
$upscope $end
$upscope $end
$upscope $end
$enddefinitions $end
#0
$dumpvars
bx x
0w
xv
b0 u
bx t
b0 s
bx r
b0 q
bx p
bx o
bx n
bx m
bx l
xk
xj
bx i
xh
xg
bx f
bx e
xd
bx c
bx b
0a
x`
b0 _
bx ^
b0 ]
bx \
b0 [
bx Z
bx Y
bx X
bx W
bx V
xU
xT
bx S
xR
xQ
bx P
bx O
xN
bx M
b0 L
bx K
bx J
bx I
bx H
bx G
bx F
bx E
bx D
bx C
b1xxxxxxxxxxxxxxxxxxxxxxx B
xA
bx @
b1xxxxxxxxxxxxxxxxxxxxxxx000000000000000000000000 ?
x>
x=
bx <
bx ;
b1xxxxxxxxxxxxxxxxxxxxxxx :
x9
bx 8
bx 7
b1xxxxxxxxxxxxxxxxxxxxxxx 6
x5
x4
bx 3
bx 2
x1
bx 0
bx /
bx .
bx -
b1xxxxxxxxxxxxxxxxxxxxxxx ,
x+
x*
bx )
1(
bx '
bx &
x%
0$
bx #
1"
1!
$end
#2500
b111111100000000000000000000000 W
b111111100000000000000000000000 V
b1000000000000000000000000000000 S
0T
b0 Z
b0x [
b111111101100000000000000000000 m
b111111000000000000000000000000 l
b111111001100000000000000000000 i
1j
b0 p
b0x q
b1 I
b0 P
b0 ^
b0 O
b0 \
0Q
0`
0R
b0 Y
0U
b0 X
b0 f
b0 t
b0 e
b0 r
0g
0v
0h
b0 o
0k
b0 n
b0 H
0"
#5000
b1 I
b0 b
b0 x
0(
#10000
1(
#15000
0(
#20000
1(
#25000
0(
#30000
1(
#35000
0(
#40000
1(
#45000
0(
#50000
1(
1"
#55000
b0 0
04
0=
01
0*
b100000000000000000000000 #
b100000000000000000000000 2
b100000000000000000000000 G
b100000000000000000000000 M
b100000000000000000000000 c
b10000001 D
b0 /
0>
b1000000000000000000000000000000000000000000000000 )
b1000000000000000000000000000000000000000000000000 F
b1 E
0A
0+
b100000000000000000000000000000000000000000000000 .
b0 @
b0 C
b0 -
b100000000000000000000000000000000000000000000000 ?
b100000000000000000000000 B
b100000000000000000000000 ,
05
b0 7
b10000000000000000000000000000000000000000000000 3
b100000000000000000000000 6
09
b0 ;
b100000000000000000000000 :
b0 [
b0 q
0%
b0 &
b0 8
b0 K
b0 '
b0 <
b0 J
1N
b0x X
b0x n
b1 H
0(
#60000
1(
#65000
b0x q
b1 [
b0 n
b0 X
0(
#70000
1(
#75000
b111111100000000000000000000000 _
b111111100000000000000000000000 ]
1a
b10 [
b0 q
b1 X
b0x n
0(
#80000
1(
#85000
b1000000000000000000000000000000 #
b1000000000000000000000000000000 2
b1000000000000000000000000000000 G
b1000000000000000000000000000000 M
b1000000000000000000000000000000 c
b10000000 E
b1111111 D
b1111111 -
b100000000000000000000000000000000000000000000000 .
b0 @
b1111111 C
b1111111 7
b1111111 ;
b0x q
1$
b111111100000000000000000000000 &
b111111100000000000000000000000 8
b111111100000000000000000000000 K
b111111100000000000000000000000 '
b111111100000000000000000000000 <
b111111100000000000000000000000 J
b1 Z
b0 _
b0 ]
0a
b1 [
b0 n
b111111100000000000000000000000 P
b111111100000000000000000000000 ^
b111111100000000000000000000000 O
b111111100000000000000000000000 \
1Q
1`
b10 X
0(
#90000
1(
#95000
b100000000000000000000000 #
b100000000000000000000000 2
b100000000000000000000000 G
b100000000000000000000000 M
b100000000000000000000000 c
b1 E
b10000001 D
b0 C
b100000000000000000000000000000000000000000000000 .
b0 @
b0 -
b0 7
b0 ;
b0 &
b0 8
b0 K
b0 '
b0 <
b0 J
0$
b111111101100000000000000000000 W
b111111000000000000000000000000 V
b111111111100000000000000000000 S
b111111000000000000000000000000 _
b111111101100000000000000000000 ]
1a
b10 [
b0 q
b0 P
b0 ^
b0 O
b0 \
0Q
0`
b1 Y
b1 X
b0x n
0(
#100000
1(
#105000
b11100000000000000000000 0
b111111111100000000000000000000 #
b111111111100000000000000000000 2
b111111111100000000000000000000 G
b111111111100000000000000000000 M
b111111111100000000000000000000 c
b1111000000000000000000000000000000000000000000000 F
b1111111 E
b111100000000000000000000000000000000000000000000 )
b1111110 D
b1100000000000000000000 /
b1111110 -
b10000000000000000000000000000000000000000000000 .
b1 @
b1111111 C
b101100000000000000000000000000000000000000000000 ?
b101100000000000000000000 B
b1111110 7
b1111111 ;
b10110000000000000000000000000000000000000000000 3
b101100000000000000000000 :
b0x q
1$
b111111000000000000000000000000 &
b111111000000000000000000000000 8
b111111000000000000000000000000 K
b111111101100000000000000000000 '
b111111101100000000000000000000 <
b111111101100000000000000000000 J
b10 Z
b0 _
b0 ]
0a
b1 [
b0 n
b111111000000000000000000000000 P
b111111000000000000000000000000 ^
b111111101100000000000000000000 O
b111111101100000000000000000000 \
1Q
1`
b10 X
0(
#110000
1(
#115000
b0 0
b100000000000000000000000 #
b100000000000000000000000 2
b100000000000000000000000 G
b100000000000000000000000 M
b100000000000000000000000 c
b1000000000000000000000000000000000000000000000000 F
b1 E
b10000001 D
b1000000000000000000000000000000000000000000000000 )
b0 /
b0 C
b100000000000000000000000000000000000000000000000 .
b0 @
b0 -
b100000000000000000000000000000000000000000000000 ?
b100000000000000000000000 B
b0 7
b0 ;
b10000000000000000000000000000000000000000000000 3
b100000000000000000000000 :
b0 &
b0 8
b0 K
b0 '
b0 <
b0 J
0$
b111111101101001111110111110100 W
b111101000000001010110111110101 V
b111111101110010000001101100100 S
b111101000000001010110111110101 _
b111111101101001111110111110100 ]
1a
b10 [
b0 q
b0 P
b0 ^
b0 O
b0 \
0Q
0`
b10 Y
b1 X
b0x n
0(
#120000
1(
